piksi_tools/__init__.py
piksi_tools/_version.py
piksi_tools/acq_plot.py
piksi_tools/acq_results.py
piksi_tools/action_logger.py
piksi_tools/almanac.py
piksi_tools/bootload_v3.py
piksi_tools/diagnostics.py
piksi_tools/fileio.py
piksi_tools/heartbeat.py
piksi_tools/interpolate_event_positions.py
piksi_tools/log_wrapper.py
piksi_tools/recover_ftdi.py
piksi_tools/sbp_msg_2_csv.py
piksi_tools/sbpjson_expand.py
piksi_tools/serial_link.py
piksi_tools/settings.py
piksi_tools/simulator_almanac_generator.py
piksi_tools/stm_unique_id.py
piksi_tools/timeout.py
piksi_tools/utils.py
piksi_tools-4.0.0.dist-info/LICENSE
piksi_tools-4.0.0.dist-info/METADATA
piksi_tools-4.0.0.dist-info/WHEEL
piksi_tools-4.0.0.dist-info/top_level.txt
piksi_tools-4.0.0.dist-info/RECORD
