Metadata-Version: 2.1
Name: piksi-tools
Version: 4.0.0
Summary: Python tools for the Piksi GNSS receiver.
Home-page: https://github.com/swift-nav/piksi_tools
Author: Swift Navigation, Inc.
Author-email: dev@swift-nav.com
License: BSD 3-Clause License
Classifier: Intended Audience :: Developers
Classifier: Intended Audience :: Science/Research
Classifier: Operating System :: POSIX :: Linux
Classifier: Operating System :: MacOS :: MacOS X
Classifier: Operating System :: Microsoft :: Windows
Classifier: Programming Language :: Python
Classifier: Topic :: Scientific/Engineering :: Interface Engine/Protocol Translator
Classifier: Topic :: Software Development :: Libraries :: Python Modules
Classifier: Programming Language :: Python :: 3.7
Classifier: Programming Language :: Python :: 3.8
Classifier: Programming Language :: Python :: 3.9
Classifier: Programming Language :: Python :: 3.10
Classifier: Programming Language :: Python :: 3.11
License-File: LICENSE
Requires-Dist: numpy
Requires-Dist: configparser
Requires-Dist: pyserial
Requires-Dist: six
Requires-Dist: monotonic
Requires-Dist: PyYAML
Requires-Dist: libsettings
Requires-Dist: sbp
Provides-Extra: ftdi
Requires-Dist: pylibftdi ; extra == 'ftdi'
Provides-Extra: test
Requires-Dist: pytest ; extra == 'test'
Requires-Dist: pytest-faulthandler ; extra == 'test'
